{
"type": "FeatureCollection",
"name": "train_station",
"crs": { "type": "name", "properties": { "name": "urn:ogc:def:crs:OGC:1.3:CRS84" } },
"features": [
{ "type": "Feature", "properties": { "Name": "Сельма", "address": "Генерала Челнокова, 13а, Калининград" }, "geometry": { "type": "Point", "coordinates": [ 20.485971473328867, 54.73864807612096 ] } },
{ "type": "Feature", "properties": { "Name": "Кутузово-Новое", "address": "Александра Невского, 179 к1, Калининград" }, "geometry": { "type": "Point", "coordinates": [ 20.534140039484072, 54.746410020043328 ] } },
{ "type": "Feature", "properties": { "Name": "Дзержинская", "address": "Двинской переулок, 13, Калининград" }, "geometry": { "type": "Point", "coordinates": [ 20.530310012647107, 54.662849989097026 ] } },
{ "type": "Feature", "properties": { "Name": "Лесное-Новое", "address": "Сержанта Бурыхина, 14а, Калининград" }, "geometry": { "type": "Point", "coordinates": [ 20.362862096669264, 54.730047400916476 ] } }
]
}
