{
"type": "FeatureCollection",
"crs": { "type": "name", "properties": { "name": "urn:ogc:def:crs:OGC:1.3:CRS84" } },
"features": [
{ "type": "Feature", "properties": { "Name": "Кутузово-Новое", "address": "Александра Невского, 179 к1, Калининград", "bbox_north": 54.7786843, "bbox_south": 54.6306222, "bbox_east": 20.653798, "bbox_west": 20.293279, "place_id": 308093923, "osm_type": "relation", "osm_id": 1674442, "lat": 54.710128, "lon": 20.5105838, "display_name": "Kaliningrad, Northwestern Federal District, Russia", "class": "place", "type": "city", "importance": 0.6115327056574722 }, "geometry": { "type": "Point", "coordinates": [ 20.534140039484072, 54.746410020043328 ] } },
{ "type": "Feature", "properties": { "Name": "Дзержинская", "address": "Двинской переулок, 13, Калининград", "bbox_north": 54.7786843, "bbox_south": 54.6306222, "bbox_east": 20.653798, "bbox_west": 20.293279, "place_id": 308093923, "osm_type": "relation", "osm_id": 1674442, "lat": 54.710128, "lon": 20.5105838, "display_name": "Kaliningrad, Northwestern Federal District, Russia", "class": "place", "type": "city", "importance": 0.6115327056574722 }, "geometry": { "type": "Point", "coordinates": [ 20.530310012647107, 54.662849989097026 ] } },
{ "type": "Feature", "properties": { "Name": "Сельма", "address": "Генерала Челнокова, 13а, Калининград", "bbox_north": 54.7786843, "bbox_south": 54.6306222, "bbox_east": 20.653798, "bbox_west": 20.293279, "place_id": 308093923, "osm_type": "relation", "osm_id": 1674442, "lat": 54.710128, "lon": 20.5105838, "display_name": "Kaliningrad, Northwestern Federal District, Russia", "class": "place", "type": "city", "importance": 0.6115327056574722 }, "geometry": { "type": "Point", "coordinates": [ 20.483853741084204, 54.73815061314172 ] } },
{ "type": "Feature", "properties": { "Name": "Лесное-Новое", "address": "Сержанта Бурыхина, 14а, Калининград", "bbox_north": 54.7786843, "bbox_south": 54.6306222, "bbox_east": 20.653798, "bbox_west": 20.293279, "place_id": 308093923, "osm_type": "relation", "osm_id": 1674442, "lat": 54.710128, "lon": 20.5105838, "display_name": "Kaliningrad, Northwestern Federal District, Russia", "class": "place", "type": "city", "importance": 0.6115327056574722 }, "geometry": { "type": "Point", "coordinates": [ 20.364679594452657, 54.728483510591765 ] } }
]
}
