{
"type": "FeatureCollection",
"features": [
{ "type": "Feature", "properties": { "Name": "ГБУЗ Ко Гкбсмп Городская клиническая больница скорой медицинской помощи", "address": "ул. Александра Невского, 90, Калининград", "latitude": 54.740579987289998, "longitude": 20.535590024914001 }, "geometry": { "type": "Point", "coordinates": [ 20.535590024914001, 54.740579987289998 ] } }
]
}
